bananopie_bns/__init__.py
bananopie_bns/constants.py
bananopie_bns/resolver.py
bananopie_bns/util.py
bananopie_bns-0.0.3.dist-info/LICENSE
bananopie_bns-0.0.3.dist-info/METADATA
bananopie_bns-0.0.3.dist-info/WHEEL
bananopie_bns-0.0.3.dist-info/top_level.txt
bananopie_bns-0.0.3.dist-info/RECORD
