Metadata-Version: 2.1
Name: bananopie_bns
Version: 0.0.3
Summary: A python library to simplify sending and receiving Banano. Also a RPC wrapper.
Home-page: https://github.com/jetstream0/bananopie_bns
Author: John Though
Author-email: prussia@prussia.dev
License: MIT
Classifier: Programming Language :: Python :: 3
Classifier: License :: OSI Approved :: MIT License
Classifier: Operating System :: OS Independent
Requires-Python: >=3.5
License-File: LICENSE
Requires-Dist: bananopie
